{"commitInfo":{"timestamp":1768076255164,"operation":"WRITE","operationParameters":{"mode":"Overwrite","partitionBy":"[]"},"readVersion":2,"isolationLevel":"Serializable","isBlindAppend":false,"operationMetrics":{"numFiles":"1","numOutputRows":"4","numOutputBytes":"1658"},"engineInfo":"Apache-Spark/3.4.1 Delta-Lake/2.4.0","txnId":"4a88e6f3-6a9b-423b-9899-705966595f44"}}
{"add":{"path":"part-00000-64a511f8-884b-45ae-a284-2394a7ad5162-c000.snappy.parquet","partitionValues":{},"size":1658,"modificationTime":1768076254807,"dataChange":true,"stats":"{\"numRecords\":4,\"minValues\":{\"symbol\":\"AAPL\",\"avg_price\":140.4466666666667,\"total_volume\":12944,\"avg_volatility\":1.92,\"pct_upward\":0.0},\"maxValues\":{\"symbol\":\"TSLA\",\"avg_price\":3396.53,\"total_volume\":114469,\"avg_volatility\":4.79,\"pct_upward\":100.0},\"nullCount\":{\"symbol\":0,\"avg_price\":0,\"total_volume\":0,\"avg_volatility\":0,\"pct_upward\":0}}"}}
{"remove":{"path":"part-00000-e3c3b62c-f7a9-4fc4-bff0-838ced65a286-c000.snappy.parquet","deletionTimestamp":1768076255163,"dataChange":true,"extendedFileMetadata":true,"partitionValues":{},"size":1661}}
