{"commitInfo":{"timestamp":1768077352746,"operation":"WRITE","operationParameters":{"mode":"Append","partitionBy":"[]"},"readVersion":50,"isolationLevel":"Serializable","isBlindAppend":true,"operationMetrics":{"numFiles":"1","numOutputRows":"100","numOutputBytes":"7252"},"engineInfo":"Apache-Spark/3.4.1 Delta-Lake/2.4.0","txnId":"5b2b018c-f627-4393-bba8-a9353e1830ee"}}
{"add":{"path":"part-00000-11fd9dc8-90c5-41c2-bf87-e302321ccd4e-c000.snappy.parquet","partitionValues":{},"size":7252,"modificationTime":1768077352759,"dataChange":true,"stats":"{\"numRecords\":100,\"minValues\":{\"timestamp\":\"2026-01-10T20:31:05.959Z\",\"symbol\":\"AAPL\",\"price\":163.37,\"volume\":1268,\"rsi\":20.38,\"macd\":-1.86,\"volatility\":0.53,\"price_change\":-2.96,\"price_direction\":0,\"volume_change\":-999},\"maxValues\":{\"timestamp\":\"2026-01-10T20:32:42.326Z\",\"symbol\":\"TSLA\",\"price\":3428.46,\"volume\":49963,\"rsi\":78.07,\"macd\":2.0,\"volatility\":4.99,\"price_change\":2.98,\"price_direction\":1,\"volume_change\":981},\"nullCount\":{\"timestamp\":0,\"symbol\":0,\"price\":0,\"volume\":0,\"rsi\":0,\"macd\":0,\"volatility\":0,\"price_change\":0,\"price_direction\":0,\"volume_change\":0}}"}}
