{"commitInfo":{"timestamp":1767801998519,"operation":"STREAMING UPDATE","operationParameters":{"outputMode":"Append","queryId":"5b09b6bd-9e4d-4cc3-949d-1dbea0427af2","epochId":"867"},"readVersion":866,"isolationLevel":"Serializable","isBlindAppend":true,"operationMetrics":{"numRemovedFiles":"0","numOutputRows":"1","numOutputBytes":"2020","numAddedFiles":"1"},"engineInfo":"Apache-Spark/3.5.1 Delta-Lake/3.2.0","txnId":"8c03a804-bbbe-445d-8aa5-c4da322b48d0"}}
{"txn":{"appId":"5b09b6bd-9e4d-4cc3-949d-1dbea0427af2","version":867,"lastUpdated":1767801998519}}
{"add":{"path":"date=2026-01-07/part-00000-613b62cf-cb31-4e31-ba70-2b748884b222.c000.snappy.parquet","partitionValues":{"date":"2026-01-07"},"size":2020,"modificationTime":1767801998514,"dataChange":true,"stats":"{\"numRecords\":1,\"minValues\":{\"symbol\":\"NVDA\",\"price\":189.74,\"volume\":0,\"open\":190.43,\"high\":189.74,\"low\":189.74,\"timestamp\":\"2026-01-07T16:06:36.785Z\"},\"maxValues\":{\"symbol\":\"NVDA\",\"price\":189.74,\"volume\":0,\"open\":190.43,\"high\":189.74,\"low\":189.74,\"timestamp\":\"2026-01-07T16:06:36.785Z\"},\"nullCount\":{\"symbol\":0,\"price\":0,\"volume\":0,\"open\":0,\"high\":0,\"low\":0,\"timestamp\":0}}"}}
