{"commitInfo":{"timestamp":1767185746031,"operation":"STREAMING UPDATE","operationParameters":{"outputMode":"Append","queryId":"5b09b6bd-9e4d-4cc3-949d-1dbea0427af2","epochId":"0"},"isolationLevel":"Serializable","isBlindAppend":true,"operationMetrics":{"numRemovedFiles":"0","numOutputRows":"0","numOutputBytes":"0","numAddedFiles":"0"},"engineInfo":"Apache-Spark/3.5.1 Delta-Lake/3.2.0","txnId":"a537f407-2ef1-4980-8469-d46c3a5c6446"}}
{"metaData":{"id":"7b3fe1cc-c04b-4a9e-be74-21528074e57e","format":{"provider":"parquet","options":{}},"schemaString":"{\"type\":\"struct\",\"fields\":[{\"name\":\"symbol\",\"type\":\"string\",\"nullable\":true,\"metadata\":{}},{\"name\":\"price\",\"type\":\"double\",\"nullable\":true,\"metadata\":{}},{\"name\":\"volume\",\"type\":\"long\",\"nullable\":true,\"metadata\":{}},{\"name\":\"open\",\"type\":\"double\",\"nullable\":true,\"metadata\":{}},{\"name\":\"high\",\"type\":\"double\",\"nullable\":true,\"metadata\":{}},{\"name\":\"low\",\"type\":\"double\",\"nullable\":true,\"metadata\":{}},{\"name\":\"timestamp\",\"type\":\"timestamp\",\"nullable\":true,\"metadata\":{}},{\"name\":\"date\",\"type\":\"date\",\"nullable\":true,\"metadata\":{}}]}","partitionColumns":["date"],"configuration":{},"createdTime":1767185742977}}
{"protocol":{"minReaderVersion":1,"minWriterVersion":2}}
{"txn":{"appId":"5b09b6bd-9e4d-4cc3-949d-1dbea0427af2","version":0,"lastUpdated":1767185745987}}
