{"commitInfo":{"timestamp":1767799730596,"operation":"STREAMING UPDATE","operationParameters":{"outputMode":"Append","queryId":"5b09b6bd-9e4d-4cc3-949d-1dbea0427af2","epochId":"737"},"readVersion":736,"isolationLevel":"Serializable","isBlindAppend":true,"operationMetrics":{"numRemovedFiles":"0","numOutputRows":"1","numOutputBytes":"2019","numAddedFiles":"1"},"engineInfo":"Apache-Spark/3.5.1 Delta-Lake/3.2.0","txnId":"35b55eb8-4efe-4edd-9c0d-363bdfb4ad1d"}}
{"txn":{"appId":"5b09b6bd-9e4d-4cc3-949d-1dbea0427af2","version":737,"lastUpdated":1767799730596}}
{"add":{"path":"date=2026-01-07/part-00000-3834d916-cfd4-478e-a7d0-937c3c9f697d.c000.snappy.parquet","partitionValues":{"date":"2026-01-07"},"size":2019,"modificationTime":1767799730589,"dataChange":true,"stats":"{\"numRecords\":1,\"minValues\":{\"symbol\":\"META\",\"price\":645.47,\"volume\":0,\"open\":659.8,\"high\":645.23,\"low\":645.23,\"timestamp\":\"2026-01-07T15:28:47.491Z\"},\"maxValues\":{\"symbol\":\"META\",\"price\":645.47,\"volume\":0,\"open\":659.8,\"high\":645.23,\"low\":645.23,\"timestamp\":\"2026-01-07T15:28:47.491Z\"},\"nullCount\":{\"symbol\":0,\"price\":0,\"volume\":0,\"open\":0,\"high\":0,\"low\":0,\"timestamp\":0}}"}}
