{"commitInfo":{"timestamp":1767445398380,"operation":"WRITE","operationParameters":{"mode":"Append","partitionBy":"[]"},"readVersion":153,"isolationLevel":"Serializable","isBlindAppend":true,"operationMetrics":{"numFiles":"2","numOutputRows":"1","numOutputBytes":"2277"},"engineInfo":"Apache-Spark/3.5.1 Delta-Lake/3.2.0","txnId":"3bf10ab4-6d45-4337-aef9-bb3f6950b90f"}}
{"add":{"path":"part-00031-cd509c73-b781-4547-be34-06c0b72fc3ea-c000.snappy.parquet","partitionValues":{},"size":1588,"modificationTime":1767445397112,"dataChange":true,"stats":"{\"numRecords\":1,\"minValues\":{\"symbol\":\"META\",\"avg_price\":650.41,\"price_volatility\":0.0,\"total_volume\":361016,\"avg_price_change\":-1.9935507202700289},\"maxValues\":{\"symbol\":\"META\",\"avg_price\":650.41,\"price_volatility\":0.0,\"total_volume\":361016,\"avg_price_change\":-1.9935507202700289},\"nullCount\":{\"symbol\":0,\"avg_price\":0,\"price_volatility\":0,\"total_volume\":0,\"avg_price_change\":0}}"}}
