{"commitInfo":{"timestamp":1767791923556,"operation":"WRITE","operationParameters":{"mode":"Append","partitionBy":"[]"},"readVersion":199,"isolationLevel":"Serializable","isBlindAppend":true,"operationMetrics":{"numFiles":"3","numOutputRows":"2","numOutputBytes":"3864"},"engineInfo":"Apache-Spark/3.5.1 Delta-Lake/3.2.0","txnId":"6767e284-e10e-4dec-af6a-c1212fc7203c"}}
{"add":{"path":"part-00076-02d617df-f66a-40a3-a9fa-9535db92e0d4-c000.snappy.parquet","partitionValues":{},"size":1588,"modificationTime":1767791921839,"dataChange":true,"stats":"{\"numRecords\":1,\"minValues\":{\"symbol\":\"NFLX\",\"avg_price\":90.65,\"price_volatility\":0.0,\"total_volume\":22623,\"avg_price_change\":-0.2859971400285897},\"maxValues\":{\"symbol\":\"NFLX\",\"avg_price\":90.65,\"price_volatility\":0.0,\"total_volume\":22623,\"avg_price_change\":-0.2859971400285897},\"nullCount\":{\"symbol\":0,\"avg_price\":0,\"price_volatility\":0,\"total_volume\":0,\"avg_price_change\":0}}"}}
{"add":{"path":"part-00191-5504f6f9-ced8-4f4f-b615-5199af2df834-c000.snappy.parquet","partitionValues":{},"size":1587,"modificationTime":1767791921860,"dataChange":true,"stats":"{\"numRecords\":1,\"minValues\":{\"symbol\":\"NVDA\",\"avg_price\":187.24,\"price_volatility\":0.0,\"total_volume\":41104,\"avg_price_change\":-2.3316467581242497},\"maxValues\":{\"symbol\":\"NVDA\",\"avg_price\":187.24,\"price_volatility\":0.0,\"total_volume\":41104,\"avg_price_change\":-2.3316467581242497},\"nullCount\":{\"symbol\":0,\"avg_price\":0,\"price_volatility\":0,\"total_volume\":0,\"avg_price_change\":0}}"}}
