{"commitInfo":{"timestamp":1767445295696,"operation":"WRITE","operationParameters":{"mode":"Append","partitionBy":"[]"},"readVersion":137,"isolationLevel":"Serializable","isBlindAppend":true,"operationMetrics":{"numFiles":"2","numOutputRows":"1","numOutputBytes":"2277"},"engineInfo":"Apache-Spark/3.5.1 Delta-Lake/3.2.0","txnId":"45a8103a-73fb-4505-b81e-d8849c322012"}}
{"add":{"path":"part-00031-2668321c-1f11-4417-8ba6-0f4dd11d6c21-c000.snappy.parquet","partitionValues":{},"size":1588,"modificationTime":1767445294461,"dataChange":true,"stats":"{\"numRecords\":1,\"minValues\":{\"symbol\":\"META\",\"avg_price\":650.41,\"price_volatility\":0.0,\"total_volume\":180508,\"avg_price_change\":-1.9935507202700289},\"maxValues\":{\"symbol\":\"META\",\"avg_price\":650.41,\"price_volatility\":0.0,\"total_volume\":180508,\"avg_price_change\":-1.9935507202700289},\"nullCount\":{\"symbol\":0,\"avg_price\":0,\"price_volatility\":0,\"total_volume\":0,\"avg_price_change\":0}}"}}
