{"commitInfo":{"timestamp":1767445402159,"operation":"WRITE","operationParameters":{"mode":"Append","partitionBy":"[]"},"readVersion":154,"isolationLevel":"Serializable","isBlindAppend":true,"operationMetrics":{"numFiles":"3","numOutputRows":"2","numOutputBytes":"3865"},"engineInfo":"Apache-Spark/3.5.1 Delta-Lake/3.2.0","txnId":"2fe257c0-647f-4de8-a417-565a9b7b9169"}}
{"add":{"path":"part-00076-96067286-cb50-439d-ba46-3e4e0f2bd513-c000.snappy.parquet","partitionValues":{},"size":1588,"modificationTime":1767445400866,"dataChange":true,"stats":"{\"numRecords\":1,\"minValues\":{\"symbol\":\"NFLX\",\"avg_price\":90.99,\"price_volatility\":0.0,\"total_volume\":1025514,\"avg_price_change\":-2.861108145617601},\"maxValues\":{\"symbol\":\"NFLX\",\"avg_price\":90.99,\"price_volatility\":0.0,\"total_volume\":1025514,\"avg_price_change\":-2.861108145617601},\"nullCount\":{\"symbol\":0,\"avg_price\":0,\"price_volatility\":0,\"total_volume\":0,\"avg_price_change\":0}}"}}
{"add":{"path":"part-00191-54d032e7-7f19-40cd-b2dc-68ba12487c6a-c000.snappy.parquet","partitionValues":{},"size":1588,"modificationTime":1767445400853,"dataChange":true,"stats":"{\"numRecords\":1,\"minValues\":{\"symbol\":\"NVDA\",\"avg_price\":188.85,\"price_volatility\":0.0,\"total_volume\":2696352,\"avg_price_change\":-0.4743083003952599},\"maxValues\":{\"symbol\":\"NVDA\",\"avg_price\":188.85,\"price_volatility\":0.0,\"total_volume\":2696352,\"avg_price_change\":-0.4743083003952599},\"nullCount\":{\"symbol\":0,\"avg_price\":0,\"price_volatility\":0,\"total_volume\":0,\"avg_price_change\":0}}"}}
