{"commitInfo":{"timestamp":1767791858481,"operation":"WRITE","operationParameters":{"mode":"Append","partitionBy":"[]"},"readVersion":189,"isolationLevel":"Serializable","isBlindAppend":true,"operationMetrics":{"numFiles":"2","numOutputRows":"1","numOutputBytes":"2284"},"engineInfo":"Apache-Spark/3.5.1 Delta-Lake/3.2.0","txnId":"4cdb32ee-1907-4da8-a469-fe8348f9114f"}}
{"add":{"path":"part-00108-469d93b1-3b14-4a95-9d59-f96725d353ea-c000.snappy.parquet","partitionValues":{},"size":1595,"modificationTime":1767791856129,"dataChange":true,"stats":"{\"numRecords\":1,\"minValues\":{\"symbol\":\"GOOGL\",\"avg_price\":314.34,\"price_volatility\":0.0,\"total_volume\":28204,\"avg_price_change\":-1.029564560309826},\"maxValues\":{\"symbol\":\"GOOGL\",\"avg_price\":314.34,\"price_volatility\":0.0,\"total_volume\":28204,\"avg_price_change\":-1.029564560309826},\"nullCount\":{\"symbol\":0,\"avg_price\":0,\"price_volatility\":0,\"total_volume\":0,\"avg_price_change\":0}}"}}
