{"commitInfo":{"timestamp":1767191162218,"operation":"WRITE","operationParameters":{"mode":"Append","partitionBy":"[]"},"readVersion":36,"isolationLevel":"Serializable","isBlindAppend":true,"operationMetrics":{"numFiles":"3","numOutputRows":"2","numOutputBytes":"3865"},"engineInfo":"Apache-Spark/3.5.1 Delta-Lake/3.2.0","txnId":"3954a49b-b0a2-46dc-9717-14375ed43356"}}
{"add":{"path":"part-00176-c9a8ace3-ee5c-40b3-b30a-2e2c4045c11d-c000.snappy.parquet","partitionValues":{},"size":1588,"modificationTime":1767191160671,"dataChange":true,"stats":"{\"numRecords\":1,\"minValues\":{\"symbol\":\"AMZN\",\"avg_price\":232.53,\"price_volatility\":0.0,\"total_volume\":390968,\"avg_price_change\":0.6623376623376629},\"maxValues\":{\"symbol\":\"AMZN\",\"avg_price\":232.53,\"price_volatility\":0.0,\"total_volume\":390968,\"avg_price_change\":0.6623376623376629},\"nullCount\":{\"symbol\":0,\"avg_price\":0,\"price_volatility\":0,\"total_volume\":0,\"avg_price_change\":0}}"}}
{"add":{"path":"part-00177-2b1246cc-82ce-41ee-9161-32b366370c2e-c000.snappy.parquet","partitionValues":{},"size":1588,"modificationTime":1767191160637,"dataChange":true,"stats":"{\"numRecords\":1,\"minValues\":{\"symbol\":\"MSFT\",\"avg_price\":487.48,\"price_volatility\":0.0,\"total_volume\":309588,\"avg_price_change\":0.563176895306863},\"maxValues\":{\"symbol\":\"MSFT\",\"avg_price\":487.48,\"price_volatility\":0.0,\"total_volume\":309588,\"avg_price_change\":0.563176895306863},\"nullCount\":{\"symbol\":0,\"avg_price\":0,\"price_volatility\":0,\"total_volume\":0,\"avg_price_change\":0}}"}}
