{"commitInfo":{"timestamp":1767794551583,"operation":"WRITE","operationParameters":{"mode":"Append","partitionBy":"[]"},"readVersion":554,"isolationLevel":"Serializable","isBlindAppend":true,"operationMetrics":{"numFiles":"2","numOutputRows":"1","numOutputBytes":"2276"},"engineInfo":"Apache-Spark/3.5.1 Delta-Lake/3.2.0","txnId":"891d75f0-c476-462b-b477-e4fb7beead3c"}}
{"add":{"path":"part-00191-39d2077d-3c8a-4008-a551-c460133a813c-c000.snappy.parquet","partitionValues":{},"size":1587,"modificationTime":1767794550366,"dataChange":true,"stats":"{\"numRecords\":1,\"minValues\":{\"symbol\":\"NVDA\",\"avg_price\":187.24,\"price_volatility\":0.0,\"total_volume\":41104,\"avg_price_change\":-2.3316467581242497},\"maxValues\":{\"symbol\":\"NVDA\",\"avg_price\":187.24,\"price_volatility\":0.0,\"total_volume\":41104,\"avg_price_change\":-2.3316467581242497},\"nullCount\":{\"symbol\":0,\"avg_price\":0,\"price_volatility\":0,\"total_volume\":0,\"avg_price_change\":0}}"}}
