{"commitInfo":{"timestamp":1767193495343,"operation":"WRITE","operationParameters":{"mode":"Append","partitionBy":"[]"},"readVersion":90,"isolationLevel":"Serializable","isBlindAppend":true,"operationMetrics":{"numFiles":"1","numOutputRows":"1","numOutputBytes":"2807"},"engineInfo":"Apache-Spark/3.5.1 Delta-Lake/3.2.0","txnId":"ce87051b-494f-41c3-997c-c2ffc43fd0d0"}}
{"add":{"path":"part-00000-776b4ae2-f415-45c0-ab2a-d95d52fd49ec-c000.snappy.parquet","partitionValues":{},"size":2807,"modificationTime":1767193495336,"dataChange":true,"stats":"{\"numRecords\":1,\"minValues\":{\"symbol\":\"AAPL\",\"price\":273.04,\"volume\":42209,\"open\":274.0,\"high\":273.04,\"low\":272.88,\"timestamp\":\"2025-12-31T15:04:52.646Z\",\"date\":\"2025-12-31\",\"price_range\":0.160000000000025,\"price_change_pct\":-0.35036496350364216},\"maxValues\":{\"symbol\":\"AAPL\",\"price\":273.04,\"volume\":42209,\"open\":274.0,\"high\":273.04,\"low\":272.88,\"timestamp\":\"2025-12-31T15:04:52.646Z\",\"date\":\"2025-12-31\",\"price_range\":0.160000000000025,\"price_change_pct\":-0.35036496350364216},\"nullCount\":{\"symbol\":0,\"price\":0,\"volume\":0,\"open\":0,\"high\":0,\"low\":0,\"timestamp\":0,\"date\":0,\"price_range\":0,\"price_change_pct\":0}}"}}
