{"commitInfo":{"timestamp":1767794533361,"operation":"WRITE","operationParameters":{"mode":"Append","partitionBy":"[]"},"readVersion":588,"isolationLevel":"Serializable","isBlindAppend":true,"operationMetrics":{"numFiles":"1","numOutputRows":"1","numOutputBytes":"2813"},"engineInfo":"Apache-Spark/3.5.1 Delta-Lake/3.2.0","txnId":"44e34057-8f98-4685-82c0-6301c31d91a3"}}
{"add":{"path":"part-00000-da859619-cc81-43e2-ba4c-28abc1da2077-c000.snappy.parquet","partitionValues":{},"size":2813,"modificationTime":1767794533356,"dataChange":true,"stats":"{\"numRecords\":1,\"minValues\":{\"symbol\":\"GOOGL\",\"price\":314.34,\"volume\":28204,\"open\":317.61,\"high\":314.17,\"low\":314.1,\"timestamp\":\"2026-01-07T14:02:10.217Z\",\"date\":\"2026-01-07\",\"price_range\":0.06999999999999318,\"price_change_pct\":-1.029564560309826},\"maxValues\":{\"symbol\":\"GOOGL\",\"price\":314.34,\"volume\":28204,\"open\":317.61,\"high\":314.17,\"low\":314.1,\"timestamp\":\"2026-01-07T14:02:10.217Z\",\"date\":\"2026-01-07\",\"price_range\":0.06999999999999318,\"price_change_pct\":-1.029564560309826},\"nullCount\":{\"symbol\":0,\"price\":0,\"volume\":0,\"open\":0,\"high\":0,\"low\":0,\"timestamp\":0,\"date\":0,\"price_range\":0,\"price_change_pct\":0}}"}}
