{"commitInfo":{"timestamp":1768076295331,"operation":"STREAMING UPDATE","operationParameters":{"outputMode":"Append","queryId":"9e58f417-a1ed-4c27-848c-4eb7d3bc7c4c","epochId":"525"},"readVersion":12,"isolationLevel":"Serializable","isBlindAppend":true,"operationMetrics":{"numRemovedFiles":"0","numOutputRows":"7","numOutputBytes":"3302","numAddedFiles":"1"},"engineInfo":"Apache-Spark/3.4.1 Delta-Lake/2.4.0","txnId":"88c4aa1b-b74f-42b6-b499-9c8f11caeac4"}}
{"txn":{"appId":"9e58f417-a1ed-4c27-848c-4eb7d3bc7c4c","version":525,"lastUpdated":1768076295330}}
{"add":{"path":"part-00000-25e5d773-6e4c-48b4-8269-6ce2c058f731-c000.snappy.parquet","partitionValues":{},"size":3302,"modificationTime":1768076294947,"dataChange":true,"stats":"{\"numRecords\":7,\"minValues\":{\"timestamp\":\"2026-01-10T20:18:07.273512\",\"symbol\":\"AAPL\",\"price\":144.42,\"volume\":2055,\"rsi\":24.37,\"macd\":-1.97,\"volatility\":0.82,\"price_change\":0.97,\"price_direction\":1,\"volume_change\":-902},\"maxValues\":{\"timestamp\":\"2026-01-10T20:18:13.285859\",\"symbol\":\"TSLA\",\"price\":3388.08,\"volume\":42643,\"rsi\":73.21,\"macd\":1.98,\"volatility\":4.35,\"price_change\":2.93,\"price_direction\":1,\"volume_change\":914},\"nullCount\":{\"timestamp\":0,\"symbol\":0,\"price\":0,\"volume\":0,\"rsi\":0,\"macd\":0,\"volatility\":0,\"price_change\":0,\"price_direction\":0,\"volume_change\":0}}"}}
